bigquery_migrations/__init__.py
bigquery_migrations/bq_client.py
bigquery_migrations/migration.py
bigquery_migrations/migration_cli.py
bigquery_migrations/migration_dir_handler.py
bigquery_migrations/migration_factory.py
bigquery_migrations/migration_log_handler.py
bigquery_migrations/migration_manager.py
bigquery_migrations/migration_service.py
bigquery_migrations-0.5.2.dist-info/LICENSE
bigquery_migrations-0.5.2.dist-info/METADATA
bigquery_migrations-0.5.2.dist-info/WHEEL
bigquery_migrations-0.5.2.dist-info/entry_points.txt
bigquery_migrations-0.5.2.dist-info/top_level.txt
bigquery_migrations-0.5.2.dist-info/RECORD
