Metadata-Version: 2.1
Name: bigquery-migrations
Version: 0.5.2
Summary: Simple tool for writing Google BigQuery migrations
Author-email: Roland Bende <benderoland+bigquery-migrations@gmail.com>
License: MIT License
Project-URL: Homepage, https://github.com/RolandBende/python-bigquery-migrations
Keywords: migrations,bigquery
Classifier: Development Status :: 3 - Alpha
Classifier: Environment :: Console
Classifier: Intended Audience :: Developers
Classifier: License :: OSI Approved :: MIT License
Classifier: Programming Language :: Python
Classifier: Programming Language :: Python :: 3
Classifier: Programming Language :: Python :: 3.9
Classifier: Topic :: Software Development :: Libraries :: Python Modules
Classifier: Topic :: Utilities
Requires-Python: >=3.9
License-File: LICENSE
Requires-Dist: google-auth
Requires-Dist: google-cloud-bigquery
Requires-Dist: colorama
Provides-Extra: dev
Requires-Dist: autopep8<3.0.0,>=2.0.0; extra == "dev"
Requires-Dist: flake8<8.0.0,>=7.0.0; extra == "dev"
Requires-Dist: ruff<1.0.0,>=0.8.0; extra == "dev"
Requires-Dist: coverage<8.0.0,>=7.0.0; extra == "dev"
